stardag/__init__.py
stardag/base_model.py
stardag/config.py
stardag/exceptions.py
stardag/polymorphic.py
stardag/registry_asset.py
stardag/_cli/__init__.py
stardag/_cli/auth.py
stardag/_cli/config.py
stardag/_cli/credentials.py
stardag/_cli/registry.py
stardag/_core/__init__.py
stardag/_core/alias_task.py
stardag/_core/auto_task.py
stardag/_core/decorator.py
stardag/_core/hashable_set.py
stardag/_core/target_base.py
stardag/_core/task.py
stardag/_core/task_id.py
stardag/_core/task_loads.py
stardag/build/__init__.py
stardag/build/_base.py
stardag/build/_concurrent.py
stardag/build/_sequential.py
stardag/integration/__init__.py
stardag/integration/aws/__init__.py
stardag/integration/aws/s3.py
stardag/integration/modal/__init__.py
stardag/integration/modal/_app.py
stardag/integration/modal/_config.py
stardag/integration/modal/_target.py
stardag/integration/prefect/__init__.py
stardag/integration/prefect/build.py
stardag/integration/prefect/utils.py
stardag/registry/__init__.py
stardag/registry/_api_registry.py
stardag/registry/_base.py
stardag/registry/_http_client.py
stardag/registry/_lock.py
stardag/target/__init__.py
stardag/target/_base.py
stardag/target/_factory.py
stardag/target/_in_memory.py
stardag/target/serialize.py
stardag/utils/__init__.py
stardag/utils/resource_provider.py
stardag/utils/testing/__init__.py
stardag/utils/testing/dynamic_deps_dag.py
stardag/utils/testing/env.py
stardag/utils/testing/generic.py
stardag/utils/testing/helper_tasks.py
stardag/utils/testing/namepace.py
stardag/utils/testing/simple_dag.py
stardag-0.1.0.dist-info/METADATA
stardag-0.1.0.dist-info/WHEEL
stardag-0.1.0.dist-info/entry_points.txt
stardag-0.1.0.dist-info/RECORD
