Metadata-Version: 2.4
Name: stardag
Version: 0.1.0
Summary: Declarative and composable DAG framework for Python with persistent asset management
Author-email: Anders Huss <info@stardag.com>
License-Expression: Apache-2.0
Classifier: Development Status :: 4 - Beta
Classifier: Intended Audience :: Developers
Classifier: License :: OSI Approved :: Apache Software License
Classifier: Programming Language :: Python :: 3
Classifier: Programming Language :: Python :: 3.10
Classifier: Programming Language :: Python :: 3.11
Classifier: Programming Language :: Python :: 3.12
Classifier: Programming Language :: Python :: 3.13
Classifier: Programming Language :: Python :: 3.14
Classifier: Topic :: Software Development :: Libraries :: Python Modules
Requires-Python: <3.15,>=3.10
Requires-Dist: aiofiles>=25.1.0
Requires-Dist: httpx>=0.27.0
Requires-Dist: pydantic-settings>=2.7.1
Requires-Dist: pydantic>=2.8.2
Requires-Dist: tomli-w>=1.0.0
Requires-Dist: typer>=0.12.0
Requires-Dist: uuid6>=2024.7.10
Provides-Extra: modal
Requires-Dist: modal>=1.0.0; extra == 'modal'
Provides-Extra: pandas
Requires-Dist: pandas>=2.1.0; extra == 'pandas'
Provides-Extra: prefect
Requires-Dist: asyncpg>=0.30.0; (python_version >= '3.13') and extra == 'prefect'
Requires-Dist: prefect>=3.0.3; extra == 'prefect'
Provides-Extra: s3
Requires-Dist: aioboto3>=13.0.0; extra == 's3'
Requires-Dist: boto3-stubs[s3]; extra == 's3'
Requires-Dist: boto3>=1.34; extra == 's3'
Requires-Dist: botocore>=1.36; extra == 's3'
Requires-Dist: types-aioboto3[s3]; extra == 's3'
